setup.py
kav_distributions/Binomialdistribution.py
kav_distributions/Gaussiandistribution.py
kav_distributions/Generaldistribution.py
kav_distributions/__init__.py
kav_distributions.egg-info/PKG-INFO
kav_distributions.egg-info/SOURCES.txt
kav_distributions.egg-info/dependency_links.txt
kav_distributions.egg-info/not-zip-safe
kav_distributions.egg-info/top_level.txt