Metadata-Version: 1.0
Name: kav-distributions
Version: 1
Summary: Gaussian distributions practice of package upload
Home-page: UNKNOWN
Author: kavya
Author-email: kushnoor.kk@gmail.com
License: UNKNOWN
Platform: UNKNOWN
